erniePySDK/__init__.py
erniePySDK/Bloomz7B.py
erniePySDK/EmbeddingV1.py
erniePySDK/ErnieBot.py
erniePySDK/ErnieBotTurbo.py
erniePySDK/Errors.py
erniePySDK/utils/getAccessToken.py
erniepysdk-0.2.1.dist-info/LICENSE
erniepysdk-0.2.1.dist-info/METADATA
erniepysdk-0.2.1.dist-info/WHEEL
erniepysdk-0.2.1.dist-info/RECORD
