Metadata-Version: 2.1
Name: erniepysdk
Version: 0.2.1
Summary: 百度千帆大模型平台的非官方 Python SDK
Home-page: https://github.com/gty20010709/erniePySDK
License: Apache-2.0
Keywords: ernie,baidu
Author: theocheng
Author-email: zlz_gty@foxmail.com
Requires-Python: >=3.11,<4.0
Classifier: License :: OSI Approved :: Apache Software License
Classifier: Programming Language :: Python :: 3
Classifier: Programming Language :: Python :: 3.11
Requires-Dist: asyncache (>=0.3.1,<0.4.0)
Requires-Dist: cachetools (>=5.3.1,<6.0.0)
Requires-Dist: httpx (>=0.24.1,<0.25.0)
Project-URL: Repository, https://github.com/gty20010709/erniePySDK
